stock_snapshot_mcp/__init__.py
stock_snapshot_mcp/alpha_vantage_client.py
stock_snapshot_mcp/server.py
stock_snapshot_mcp-0.1.0.dist-info/licenses/LICENSE
stock_snapshot_mcp-0.1.0.dist-info/METADATA
stock_snapshot_mcp-0.1.0.dist-info/WHEEL
stock_snapshot_mcp-0.1.0.dist-info/entry_points.txt
stock_snapshot_mcp-0.1.0.dist-info/top_level.txt
stock_snapshot_mcp-0.1.0.dist-info/RECORD
