Metadata-Version: 2.4
Name: stock-snapshot-mcp
Version: 0.1.0
Summary: A minimal, educational MCP server that provides a single stock snapshot tool using the free Alpha Vantage API.
Author: Pavatharani Senthil Kumar
License: MIT
Project-URL: Homepage, https://github.com/pforpav/stock-snapshot-mcp
Project-URL: Source, https://github.com/pforpav/stock-snapshot-mcp
Project-URL: Issues, https://github.com/pforpav/stock-snapshot-mcp/issues
Requires-Python: >=3.10
License-File: LICENSE
Requires-Dist: mcp>=0.1.0
Requires-Dist: httpx>=0.27.0
Requires-Dist: python-dotenv>=1.0.0
Dynamic: license-file
